get_rich_logger/__init__.py
get_rich_logger/_logger.py
get_rich_logger-0.4.2.dist-info/LICENSE
get_rich_logger-0.4.2.dist-info/METADATA
get_rich_logger-0.4.2.dist-info/WHEEL
get_rich_logger-0.4.2.dist-info/RECORD
